tsutils/__init__.py
tsutils/cog_mixins.py
tsutils/cog_settings.py
tsutils/converters.py
tsutils/emoji.py
tsutils/enums.py
tsutils/errors.py
tsutils/formatting.py
tsutils/helper_classes.py
tsutils/helper_functions.py
tsutils/json_utils.py
tsutils/old_menu.py
tsutils/pad.py
tsutils/time.py
tsutils/user_interaction.py
tsutils/cogs/__init__.py
tsutils/cogs/apicog.py
tsutils/cogs/donations.py
tsutils/cogs/globaladmin.py
tsutils/cogs/userpreferences.py
tsutils/menu/__init__.py
tsutils/menu/closable_embed_base.py
tsutils/menu/pad_view.py
tsutils/menu/simple_text.py
tsutils/menu/components/__init__.py
tsutils/menu/components/config.py
tsutils/menu/components/footers.py
tsutils/menu/components/panes.py
tsutils/menu/view/__init__.py
tsutils/menu/view/closable_embed.py
tsutils/menu/view/simple_text.py
tsutils/menu/view/view_state_base.py
tsutils/query_settings/__init__.py
tsutils/query_settings/converters.py
tsutils/query_settings/enums.py
tsutils/query_settings/query_settings.py
tsutils/tsubaki/__init__.py
tsutils/tsubaki/custom_emoji.py
tsutils/tsubaki/links.py
tsutils/tsubaki/monster_header.py
tsutils-8.1.0.dist-info/licenses/LICENSE
tsutils-8.1.0.dist-info/METADATA
tsutils-8.1.0.dist-info/WHEEL
tsutils-8.1.0.dist-info/top_level.txt
tsutils-8.1.0.dist-info/RECORD
