Metadata-Version: 2.4
Name: tsutils
Version: 8.1.0
Summary: A collection of helper commands for Red-DiscordBot
Author: The Tsubotki Team
Author-email: 69992611+TsubakiBotPAD@users.noreply.github.com
License: MIT
Classifier: Programming Language :: Python :: 3
Classifier: License :: OSI Approved :: MIT License
Classifier: Operating System :: OS Independent
Requires-Python: >=3.8
License-File: LICENSE
Requires-Dist: backoff==1.10.0
Requires-Dist: discord_menu>=0.16.13
Requires-Dist: Red-DiscordBot>=3.5.1
Dynamic: author
Dynamic: author-email
Dynamic: classifier
Dynamic: description
Dynamic: description-content-type
Dynamic: license
Dynamic: license-file
Dynamic: requires-dist
Dynamic: requires-python
Dynamic: summary
